al360_erroranalysis/__init__.py
al360_erroranalysis/version.py
al360_erroranalysis/_internal/__init__.py
al360_erroranalysis/_internal/cohort_filter.py
al360_erroranalysis/_internal/constants.py
al360_erroranalysis/_internal/matrix_filter.py
al360_erroranalysis/_internal/metrics.py
al360_erroranalysis/_internal/process_categoricals.py
al360_erroranalysis/_internal/surrogate_error_tree.py
al360_erroranalysis/_internal/utils.py
al360_erroranalysis/_internal/version_checker.py
al360_erroranalysis/_internal/error_analyzer/__init__.py
al360_erroranalysis/_internal/error_report/__init__.py
al360_erroranalysis/analyzer/__init__.py
al360_erroranalysis/analyzer/error_analyzer.py
al360_erroranalysis/error_correlation_methods/__init__.py
al360_erroranalysis/error_correlation_methods/ebm.py
al360_erroranalysis/error_correlation_methods/gbm.py
al360_erroranalysis/report/__init__.py
al360_erroranalysis/report/error_report.py
al360_erroranalysis-0.5.4.dist-info/LICENSE
al360_erroranalysis-0.5.4.dist-info/METADATA
al360_erroranalysis-0.5.4.dist-info/WHEEL
al360_erroranalysis-0.5.4.dist-info/top_level.txt
al360_erroranalysis-0.5.4.dist-info/RECORD
